{"web":{"client_id":"8800937726-shq7evnirigqrko6974jjf4um1sjaf75.apps.googleusercontent.com","project_id":"restaurant-menu-171923","auth_uri":"https://accounts.google.com/o/oauth2/auth","token_uri":"https://accounts.google.com/o/oauth2/token","auth_provider_x509_cert_url":"https://www.googleapis.com/oauth2/v1/certs","client_secret":"AI9u7_kADGjwI5a-lHE1ydx1","redirect_uris":["http://localhost:5000/gconnect","http://localhost:5000/login","http://localhost:5000/callback"],"javascript_origins":["http://localhost:5000","http://localhost:8000"]}}